ttrac/ttrac.py
ttrac-0.0.8.dist-info/METADATA
ttrac-0.0.8.dist-info/WHEEL
ttrac-0.0.8.dist-info/entry_points.txt
ttrac-0.0.8.dist-info/top_level.txt
ttrac-0.0.8.dist-info/RECORD
