Metadata-Version: 2.1
Name: ttrac
Version: 0.0.8
Summary: track your working times
Home-page: https://github.com/ljurk/ttrac
Author: Lukas Jurk
Author-email: ljurk@pm.me
License: GPLv3
Keywords: time work ttrac
Platform: UNKNOWN
Classifier: Programming Language :: Python :: 3
Requires-Dist: Click
